[{"vehicleListChanged":false,"Id":1,"RegistrationID":"1828920","CarManufacture":"BMW","CarModel":"Z5","CarYear":"2019","FuelType":"Petrol","TankCapacity":"7.5","VehicleOdometer":"10020"},{"vehicleListChanged":false,"Id":2,"RegistrationID":"2829121","CarManufacture":"Toyota","CarModel":"Innova","CarYear":"2014","FuelType":"Petrol","TankCapacity":"20","VehicleOdometer":"20001"},{"vehicleListChanged":true,"Id":0,"RegistrationID":"1234567","CarManufacture":"lanang1","CarModel":"Wisnugiri1","CarYear":"2019","FuelType":"diesel","TankCapacity":"80","VehicleOdometer":"1219921"},{"vehicleListChanged":false,"Id":0,"RegistrationID":"test","CarManufacture":"test","CarModel":"test","CarYear":"test","FuelType":"test","TankCapacity":"test","VehicleOdometer":"tes"},{"vehicleListChanged":false,"Id":0,"RegistrationID":"fucker","CarManufacture":"fucker","CarModel":"fucker","CarYear":"fucker","FuelType":"fucker","TankCapacity":"fucker","VehicleOdometer":"fucker"},{"vehicleListChanged":false,"Id":0,"RegistrationID":"god damn it","CarManufacture":"god damn it fuck you","CarModel":"god damn it ","CarYear":"my fuckin head is gonna blow","FuelType":"god damn it","TankCapacity":"god damn it","VehicleOdometer":"god damn it"}]